{
  "General Info": {
    "Name": "elgato stream deck",
    "Use Case": "Creative and Media Tools",
    "Homepage": "https://www.elgato.com/us/en/s/explore-stream-deck",
    "Description": null
  },
  "Documentation": {
    "Main Documentation": "https://www.elgato.com/us/en/s/setups",
    "Top Links": [
      "https://www.elgato.com/us/en/s/setups",
      "https://docs.elgato.com/sdk/",
      "https://docs.elgato.com/"
    ]
  },
  "Installation": {
    "Links": [
      "https://www.elgato.com/us/en/s/setups",
      "https://www.elgato.com/us/en/p/wave-panels-starter-set-blue"
    ],
    "Summary": {
      "pip": [],
      "from_source": [],
      "docker": [],
      "docker_compose": [],
      "other": [],
      "platforms": null
    }
  },
  "Other Links": {
    "All Documentation Links": [
      "https://www.elgato.com/us/en/s/setups",
      "https://docs.elgato.com/sdk/",
      "https://docs.elgato.com/",
      "https://docs.elgato.com/streamdeck/sdk/introduction/getting-started",
      "https://docs.elgato.com/streamdeck/sdk/guides/actions",
      "https://docs.elgato.com/streamdeck/sdk/guides/keys",
      "https://docs.elgato.com/streamdeck/sdk/guides/dials",
      "https://docs.elgato.com/streamdeck/sdk/guides/settings",
      "https://docs.elgato.com/streamdeck/sdk/guides/ui",
      "https://docs.elgato.com/streamdeck/sdk/guides/devices",
      "https://docs.elgato.com/streamdeck/sdk/guides/profiles",
      "https://docs.elgato.com/streamdeck/sdk/guides/logging",
      "https://docs.elgato.com/streamdeck/sdk/guides/deep-linking",
      "https://docs.elgato.com/streamdeck/sdk/guides/app-monitoring",
      "https://docs.elgato.com/streamdeck/sdk/guides/system",
      "https://docs.elgato.com/streamdeck/sdk/guides/i18n",
      "https://docs.elgato.com/streamdeck/sdk/guides/distribution",
      "https://docs.elgato.com/guidelines/streamdeck/plugins/metadata",
      "https://docs.elgato.com/streamdeck/sdk/style-guide/linting",
      "https://docs.elgato.com/guidelines/submissions",
      "https://github.com/nvm-sh/nvm?tab=readme-ov-file#installing-and-updating",
      "https://learn.microsoft.com/en-us/windows/dev-environment/javascript/nodejs-on-windows#install-nvm-windows-nodejs-and-npm",
      "https://docs.elgato.com/guidelines"
    ],
    "All Installation Links": [
      "https://www.elgato.com/us/en/s/setups",
      "https://www.elgato.com/us/en/p/wave-panels-starter-set-blue"
    ]
  }
}